py65/__init__.py
py65/assembler.py
py65/disassembler.py
py65/memory.py
py65/monitor.py
py65/devices/__init__.py
py65/devices/mpu6502.py
py65/devices/mpu65c02.py
py65/devices/mpu65org16.py
py65/tests/__init__.py
py65/tests/test_assembler.py
py65/tests/test_disassembler.py
py65/tests/test_memory.py
py65/tests/test_monitor.py
py65/tests/devices/__init__.py
py65/tests/devices/test_mpu6502.py
py65/tests/devices/test_mpu65c02.py
py65/tests/utils/__init__.py
py65/tests/utils/test_addressing.py
py65/tests/utils/test_console.py
py65/tests/utils/test_conversions.py
py65/tests/utils/test_devices.py
py65/utils/__init__.py
py65/utils/addressing.py
py65/utils/console.py
py65/utils/conversions.py
py65/utils/devices.py
py65-1.1.0.dist-info/DESCRIPTION.rst
py65-1.1.0.dist-info/METADATA
py65-1.1.0.dist-info/RECORD
py65-1.1.0.dist-info/WHEEL
py65-1.1.0.dist-info/entry_points.txt
py65-1.1.0.dist-info/metadata.json
py65-1.1.0.dist-info/top_level.txt
